pytest_reportlog/__init__.py
pytest_reportlog/_version.py
pytest_reportlog/plugin.py
pytest_reportlog-0.4.0.dist-info/LICENSE
pytest_reportlog-0.4.0.dist-info/METADATA
pytest_reportlog-0.4.0.dist-info/WHEEL
pytest_reportlog-0.4.0.dist-info/entry_points.txt
pytest_reportlog-0.4.0.dist-info/top_level.txt
pytest_reportlog-0.4.0.dist-info/RECORD
