Metadata-Version: 2.1
Name: pytest-reportlog
Version: 0.4.0
Summary: Replacement for the --resultlog option, focused in simplicity and extensibility
Home-page: https://github.com/pytest-dev/pytest-reportlog
Author: Bruno Oliveira
Author-email: nicoddemus@gmail.com
License: MIT
Keywords: pytest
Platform: any
Classifier: Development Status :: 3 - Alpha
Classifier: Framework :: Pytest
Classifier: Intended Audience :: Developers
Classifier: License :: OSI Approved :: MIT License
Classifier: Operating System :: OS Independent
Classifier: Programming Language :: Python :: 3
Classifier: Programming Language :: Python :: 3.7
Classifier: Programming Language :: Python :: 3.8
Classifier: Programming Language :: Python :: 3.9
Classifier: Programming Language :: Python :: 3.10
Classifier: Programming Language :: Python :: 3.11
Classifier: Topic :: Software Development :: Testing
Requires-Python: >=3.7
Provides-Extra: dev
License-File: LICENSE
